{
  "venues": [
    {
      "picpath": "ak-1",
      "picpath_over": "ak-1",
      "id": 22763732,
      "time": "2 днів тому",
      "name": "На Херсонському напрямку українські війська відбили 2 штурми російської армії, - повідомляє Генштаб ЗСУ",
      "source": "https://t.me/lumsrc/12625",
      "lat": "46.51386",
      "lng": 32.49893,
      "picture": "images/22763732_main_picture.jpg",
      "twitpic": "",
      "lang": "uk",
      "video": "",
      "gi": 0,
      "videotype": 0,
      "timestamp": 1749461640,
      "color_id": 1,
      "cat_id": 25,
      "status_id": 0,
      "description": "",
      "udescription": "",
      "picw": 39,
      "pich": 39,
      "picwo": 49,
      "picho": 49,
      "picx": 0,
      "picy": 0,
      "picxo": 0,
      "picyo": 0,
      "ps": [],
      "points": [
        {
          "id": 38,
          "lat": 46.51386,
          "lng": 32.49893
        }
      ],
      "link": "https://liveuamap.com/uk/2025/9-june-09-at-kherson-axis-ukrainian-forces-have-repelled",
      "images": [
        {},
        {},
        {}
      ],
      "otherregions": "[]",
      "location": "Kherson",
      "keywords": "",
      "resource": 0,
      "langs": "",
      "langNames": [],
      "runway": null,
      "moreSources": [],
      "videocode": null,
      "target": null,
      "sel_link": null,
      "img_share": ""
    },
    {
      "picpath": "ak-1",
      "picpath_over": "ak-1",
      "id": 22763465,
      "time": "3 днів тому",
      "name": "На Херсонському напрямку українські війська відбили 3 атаки російської армії, - повідомляє Генштаб ЗСУ",
      "source": "https://t.me/lumsrc/12613",
      "lat": "46.57056",
      "lng": 32.67746,
      "picture": "images/22763465_main_picture.jpg",
      "twitpic": "",
      "lang": "uk",
      "video": "",
      "gi": 0,
      "videotype": 0,
      "timestamp": 1749371760,
      "color_id": 1,
      "cat_id": 25,
      "status_id": 0,
      "description": "",
      "udescription": "",
      "picw": 39,
      "pich": 39,
      "picwo": 49,
      "picho": 49,
      "picx": 0,
      "picy": 0,
      "picxo": 0,
      "picyo": 0,
      "ps": [],
      "points": [
        {
          "id": 3,
          "lat": 46.57056,
          "lng": 32.67746
        }
      ],
      "link": "https://liveuamap.com/uk/2025/8-june-08-at-kherson-axis-ukrainian-forces-have-repelled",
      "images": [
        {},
        {},
        {}
      ],
      "otherregions": "[]",
      "location": "Kherson Oblast, Ukraine",
      "keywords": "",
      "resource": 0,
      "langs": "",
      "langNames": [],
      "runway": null,
      "moreSources": [],
      "videocode": null,
      "target": null,
      "sel_link": null,
      "img_share": ""
    },
    {
      "picpath": "ak-1",
      "picpath_over": "ak-1",
      "id": 22763733,
      "time": "2 днів тому",
      "name": "Вчора на Оріхівському напрямку відбулися зіткнення поблизу Новоандріївки та Павлівки, – повідомляє Генеральний штаб Збройних Сил України",
      "source": "https://t.me/lumsrc/12623",
      "lat": "47.59283",
      "lng": 35.5073,
      "picture": "images/22763733_main_picture.jpg",
      "twitpic": "",
      "lang": "uk",
      "video": "",
      "gi": 0,
      "videotype": 0,
      "timestamp": 1749456000,
      "color_id": 1,
      "cat_id": 25,
      "status_id": 0,
      "description": "",
      "udescription": "",
      "picw": 39,
      "pich": 39,
      "picwo": 49,
      "picho": 49,
      "picx": 0,
      "picy": 0,
      "picxo": 0,
      "picyo": 0,
      "ps": [],
      "points": [
        {
          "id": 0,
          "lat": 47.54859,
          "lng": 35.6975
        },
        {
          "id": 1,
          "lat": 47.59283,
          "lng": 35.5073
        }
      ],
      "link": "https://liveuamap.com/uk/2025/9-june-08-at-orikhiv-axis-clashes-yesterday-near-novoandriyivka",
      "images": [
        {},
        {},
        {}
      ],
      "otherregions": "[]",
      "location": "Zaporizhia Oblast, Ukraine",
      "keywords": "",
      "resource": 0,
      "langs": "",
      "langNames": [],
      "runway": null,
      "moreSources": [],
      "videocode": null,
      "target": null,
      "sel_link": null,
      "img_share": ""
    },
    {
      "picpath": "ak-1",
      "picpath_over": "ak-1",
      "id": 22763460,
      "time": "3 днів тому",
      "name": "На Оріхівському напрямку вчора під Новоандріївкою пролунали бойові дії, - повідомляє Генштаб ЗСУ",
      "source": "https://t.me/lumsrc/12611",
      "lat": "47.5523",
      "lng": 35.69458,
      "picture": "images/22763460_main_picture.jpg",
      "twitpic": "",
      "lang": "uk",
      "video": "",
      "gi": 0,
      "videotype": 0,
      "timestamp": 1749369600,
      "color_id": 1,
      "cat_id": 25,
      "status_id": 0,
      "description": "",
      "udescription": "",
      "picw": 39,
      "pich": 39,
      "picwo": 49,
      "picho": 49,
      "picx": 0,
      "picy": 0,
      "picxo": 0,
      "picyo": 0,
      "ps": [],
      "points": [
        {
          "id": 92,
          "lat": 47.5523,
          "lng": 35.69458
        }
      ],
      "link": "https://liveuamap.com/uk/2025/8-june-08-at-orikhiv-axis-clashes-yesterday-near-novoandriyivka",
      "images": [
        {},
        {},
        {}
      ],
      "otherregions": "[]",
      "location": "Zaporizhia Oblast, Ukraine",
      "keywords": "",
      "resource": 0,
      "langs": "",
      "langNames": [],
      "runway": null,
      "moreSources": [],
      "videocode": null,
      "target": null,
      "sel_link": null,
      "img_share": ""
    },
    {
      "picpath": "ak-1",
      "picpath_over": "ak-1",
      "id": 22763734,
      "time": "2 днів тому",
      "name": "Вчора на Гуляйпільскому напрямку відбулися зіткнення під Малинівкою, – повідомляє Генеральний штаб Збройних сил України",
      "source": "https://t.me/lumsrc/12624",
      "lat": "47.66039",
      "lng": 36.48714,
      "picture": "images/22763734_main_picture.jpg",
      "twitpic": "",
      "lang": "uk",
      "video": "",
      "gi": 0,
      "videotype": 0,
      "timestamp": 1749461640,
      "color_id": 1,
      "cat_id": 25,
      "status_id": 0,
      "description": "",
      "udescription": "",
      "picw": 39,
      "pich": 39,
      "picwo": 49,
      "picho": 49,
      "picx": 0,
      "picy": 0,
      "picxo": 0,
      "picyo": 0,
      "ps": [],
      "points": [
        {
          "id": 39,
          "lat": 47.66039,
          "lng": 36.48714
        }
      ],
      "link": "https://liveuamap.com/uk/2025/9-june-09-at-huliaipole-axis-clashes-yesterday-near-malynivka",
      "images": [
        {},
        {},
        {}
      ],
      "otherregions": "[]",
      "location": "Zaporizhzhia, Zaporiz'ka oblast",
      "keywords": "",
      "resource": 0,
      "langs": "",
      "langNames": [],
      "runway": null,
      "moreSources": [],
      "videocode": null,
      "target": null,
      "sel_link": null,
      "img_share": ""
    },
    {
      "picpath": "ak-1",
      "picpath_over": "ak-1",
      "id": 22763467,
      "time": "3 днів тому",
      "name": "Вчора в Гуляйполі відбулися зіткнення під Малинівкою, – повідомляє Генеральний штаб Збройних сил України",
      "source": "https://t.me/lumsrc/12612",
      "lat": "47.6617",
      "lng": 36.49552,
      "picture": "images/22763467_main_picture.jpg",
      "twitpic": "",
      "lang": "uk",
      "video": "",
      "gi": 0,
      "videotype": 0,
      "timestamp": 1749371760,
      "color_id": 1,
      "cat_id": 25,
      "status_id": 0,
      "description": "",
      "udescription": "",
      "picw": 39,
      "pich": 39,
      "picwo": 49,
      "picho": 49,
      "picx": 0,
      "picy": 0,
      "picxo": 0,
      "picyo": 0,
      "ps": [],
      "points": [
        {
          "id": 4,
          "lat": 47.6617,
          "lng": 36.49552
        }
      ],
      "link": "https://liveuamap.com/uk/2025/8-june-08-at-huliaipole-axis-clashes-yesterday-near-malynivka",
      "images": [
        {},
        {},
        {}
      ],
      "otherregions": "[]",
      "location": "Zaporizhzhia, Zaporiz'ka oblast",
      "keywords": "",
      "resource": 0,
      "langs": "",
      "langNames": [],
      "runway": null,
      "moreSources": [],
      "videocode": null,
      "target": null,
      "sel_link": null,
      "img_share": ""
    },
    {
      "picpath": "ak-1",
      "picpath_over": "ak-1",
      "id": 22763461,
      "time": "3 днів тому",
      "name": "На Новопавлівському напрямку вчора відбулися бої біля Багатиря, Веселого, Бурлацького та Вільного Поля, - повідомляє Генштаб ЗСУ",
      "source": "https://t.me/lumsrc/12610",
      "lat": "47.87237",
      "lng": 36.69259,
      "picture": "images/22763461_main_picture.jpg",
      "twitpic": "",
      "lang": "uk",
      "video": "",
      "gi": 0,
      "videotype": 0,
      "timestamp": 1749369600,
      "color_id": 1,
      "cat_id": 25,
      "status_id": 0,
      "description": "",
      "udescription": "",
      "picw": 39,
      "pich": 39,
      "picwo": 49,
      "picho": 49,
      "picx": 0,
      "picy": 0,
      "picxo": 0,
      "picyo": 0,
      "ps": [],
      "points": [
        {
          "id": 93,
          "lat": 48.00277,
          "lng": 36.92917
        },
        {
          "id": 94,
          "lat": 47.92793,
          "lng": 36.76641
        },
        {
          "id": 95,
          "lat": 47.88546,
          "lng": 36.73004
        },
        {
          "id": 96,
          "lat": 47.87237,
          "lng": 36.69259
        }
      ],
      "link": "https://liveuamap.com/uk/2025/8-june-08-at-novopavlivka-axis-clashes-yesterday-near-bahatyr",
      "images": [
        {},
        {},
        {}
      ],
      "otherregions": "[]",
      "location": "Donetsk Oblast, Ukraine",
      "keywords": "",
      "resource": 0,
      "langs": "",
      "langNames": [],
      "runway": null,
      "moreSources": [],
      "videocode": null,
      "target": null,
      "sel_link": null,
      "img_share": ""
    },
    {
      "picpath": "ak-1",
      "picpath_over": "ak-1",
      "id": 22763736,
      "time": "2 днів тому",
      "name": "На Новопавлівському напрямку вчора відбулися бойові дії поблизу Багатиря, Орадного, Рівнополя, Новосілки, Новополя, Вільного Поля та в бік Запоріжжя, Воскресенки та Шевченка, - повідомляє Генштаб ЗСУ",
      "source": "https://t.me/lumsrc/12622",
      "lat": "48.00909",
      "lng": 36.78377,
      "picture": "images/22763736_main_picture.jpg",
      "twitpic": "",
      "lang": "uk",
      "video": "",
      "gi": 0,
      "videotype": 0,
      "timestamp": 1749456000,
      "color_id": 1,
      "cat_id": 25,
      "status_id": 0,
      "description": "",
      "udescription": "",
      "picw": 39,
      "pich": 39,
      "picwo": 49,
      "picho": 49,
      "picx": 0,
      "picy": 0,
      "picxo": 0,
      "picyo": 0,
      "ps": [],
      "points": [
        {
          "id": 40,
          "lat": 48.00105,
          "lng": 36.9278
        },
        {
          "id": 41,
          "lat": 47.9804,
          "lng": 36.85093
        },
        {
          "id": 42,
          "lat": 47.89547,
          "lng": 36.70196
        },
        {
          "id": 43,
          "lat": 47.94735,
          "lng": 36.69331
        },
        {
          "id": 44,
          "lat": 47.82357,
          "lng": 36.64502
        },
        {
          "id": 45,
          "lat": 48.00909,
          "lng": 36.78377
        }
      ],
      "link": "https://liveuamap.com/uk/2025/9-june-08-at-novopavlivka-axis-clashes-yesterday-near-bahatyr",
      "images": [
        {},
        {},
        {}
      ],
      "otherregions": "[]",
      "location": "Donetsk Oblast, Ukraine",
      "keywords": "",
      "resource": 0,
      "langs": "",
      "langNames": [],
      "runway": null,
      "moreSources": [],
      "videocode": null,
      "target": null,
      "sel_link": null,
      "img_share": ""
    },
    {
      "picpath": "ak-1",
      "picpath_over": "ak-1",
      "id": 22763471,
      "time": "3 днів тому",
      "name": "Міністерство оборони Росії стверджує, що його війська досягли адміністративного кордону між Донецькою та Дніпропетровською областями України та просуваються на захід",
      "source": "https://t.me/tassovkaru/32435",
      "lat": "48.08341",
      "lng": 36.89591,
      "picture": "",
      "twitpic": "",
      "lang": "uk",
      "video": "",
      "gi": 0,
      "videotype": 0,
      "timestamp": 1749371880,
      "color_id": 1,
      "cat_id": 25,
      "status_id": 0,
      "description": "",
      "udescription": "",
      "picw": 39,
      "pich": 39,
      "picwo": 49,
      "picho": 49,
      "picx": 0,
      "picy": 0,
      "picxo": 0,
      "picyo": 0,
      "ps": [],
      "points": [
        {
          "id": 114,
          "lat": 48.15336,
          "lng": 36.88145
        },
        {
          "id": 115,
          "lat": 48.08341,
          "lng": 36.89591
        }
      ],
      "link": "https://liveuamap.com/uk/2025/8-june-08-russian-ministry-of-defense-claims-its-troops-reached",
      "images": [
        {},
        {}
      ],
      "otherregions": "[]",
      "location": "Donetsk Oblast, Ukraine",
      "keywords": "",
      "resource": 0,
      "langs": "",
      "langNames": [],
      "runway": null,
      "moreSources": [],
      "videocode": null,
      "target": null,
      "sel_link": null,
      "img_share": ""
    },
    {
      "picpath": "ak-1",
      "picpath_over": "ak-1",
      "id": 22763740,
      "time": "2 днів тому",
      "name": "На Покровському напрямку бойові дії вчора відбулися поблизу Миролюбівки, Малинівки, Єлизаветівки, Лисівки, Звірового, Удачного, Горіхового, Андріївки та в напрямку Мирного, Миколаївки, Проміня, Новосергіївки, Олексіївки, - повідомляє Генштаб ЗСУ.",
      "source": "https://t.me/lumsrc/12621",
      "lat": "48.01863",
      "lng": 36.96246,
      "picture": "images/22763740_main_picture.jpg",
      "twitpic": "",
      "lang": "uk",
      "video": "",
      "gi": 0,
      "videotype": 0,
      "timestamp": 1749456000,
      "color_id": 1,
      "cat_id": 25,
      "status_id": 0,
      "description": "",
      "udescription": "",
      "picw": 39,
      "pich": 39,
      "picwo": 49,
      "picho": 49,
      "picx": 0,
      "picy": 0,
      "picxo": 0,
      "picyo": 0,
      "ps": [],
      "points": [
        {
          "id": 46,
          "lat": 48.29517,
          "lng": 37.37892
        },
        {
          "id": 47,
          "lat": 48.33125,
          "lng": 37.40725
        },
        {
          "id": 48,
          "lat": 48.30682,
          "lng": 37.41308
        },
        {
          "id": 49,
          "lat": 48.22097,
          "lng": 37.27146
        },
        {
          "id": 50,
          "lat": 48.24933,
          "lng": 37.12486
        },
        {
          "id": 51,
          "lat": 48.23698,
          "lng": 37.00779
        },
        {
          "id": 52,
          "lat": 48.08921,
          "lng": 36.93651
        },
        {
          "id": 53,
          "lat": 48.03113,
          "lng": 36.99011
        },
        {
          "id": 54,
          "lat": 48.3091,
          "lng": 37.40038
        },
        {
          "id": 55,
          "lat": 48.31869,
          "lng": 37.36931
        },
        {
          "id": 56,
          "lat": 48.26524,
          "lng": 37.31901
        },
        {
          "id": 57,
          "lat": 48.20395,
          "lng": 36.97397
        },
        {
          "id": 58,
          "lat": 48.01863,
          "lng": 36.96246
        }
      ],
      "link": "https://liveuamap.com/uk/2025/9-june-08-at-pokrovsk-axis-clashes-yesterday-near-myrolubivka",
      "images": [
        {},
        {},
        {}
      ],
      "otherregions": "[]",
      "location": "Donetsk Oblast, Ukraine",
      "keywords": "",
      "resource": 0,
      "langs": "",
      "langNames": [],
      "runway": null,
      "moreSources": [],
      "videocode": null,
      "target": null,
      "sel_link": null,
      "img_share": ""
    },
    {
      "picpath": "ak-1",
      "picpath_over": "ak-1",
      "id": 22763462,
      "time": "3 днів тому",
      "name": "На Покровському напрямку бойові дії вчора відбулися поблизу Полтавки, Миролюбівки, Мирного, Єлизаветівки, Промінь, Лисівки, Новосергіївки, Удачного, Котлиного, Новомиколаївки, Горіхового, Котлярівки, Богданівки, Новоукраїнки та Андріївки, - повідомляє Генштаб ЗСУ.",
      "source": "https://t.me/lumsrc/12609",
      "lat": "48.03102",
      "lng": 37.01603,
      "picture": "images/22763462_main_picture.jpg",
      "twitpic": "",
      "lang": "uk",
      "video": "",
      "gi": 0,
      "videotype": 0,
      "timestamp": 1749369600,
      "color_id": 1,
      "cat_id": 25,
      "status_id": 0,
      "description": "",
      "udescription": "",
      "picw": 39,
      "pich": 39,
      "picwo": 49,
      "picho": 49,
      "picx": 0,
      "picy": 0,
      "picxo": 0,
      "picyo": 0,
      "ps": [],
      "points": [
        {
          "id": 97,
          "lat": 48.42565,
          "lng": 37.48072
        },
        {
          "id": 98,
          "lat": 48.29311,
          "lng": 37.38476
        },
        {
          "id": 99,
          "lat": 48.31172,
          "lng": 37.40141
        },
        {
          "id": 100,
          "lat": 48.30476,
          "lng": 37.41789
        },
        {
          "id": 101,
          "lat": 48.26592,
          "lng": 37.32176
        },
        {
          "id": 102,
          "lat": 48.21996,
          "lng": 37.26786
        },
        {
          "id": 103,
          "lat": 48.20338,
          "lng": 36.97449
        },
        {
          "id": 104,
          "lat": 48.23563,
          "lng": 37.00127
        },
        {
          "id": 105,
          "lat": 48.25049,
          "lng": 37.04607
        },
        {
          "id": 106,
          "lat": 48.18083,
          "lng": 36.93449
        },
        {
          "id": 107,
          "lat": 48.09331,
          "lng": 36.92831
        },
        {
          "id": 108,
          "lat": 48.09102,
          "lng": 36.92574
        },
        {
          "id": 109,
          "lat": 48.1364,
          "lng": 36.92471
        },
        {
          "id": 110,
          "lat": 48.0854,
          "lng": 36.96917
        },
        {
          "id": 111,
          "lat": 48.22522,
          "lng": 37.18529
        },
        {
          "id": 112,
          "lat": 48.03102,
          "lng": 37.01603
        }
      ],
      "link": "https://liveuamap.com/uk/2025/8-june-08-at-pokrovsk-axis-clashes-yesterday-near--poltavka",
      "images": [
        {},
        {},
        {}
      ],
      "otherregions": "[]",
      "location": "Donetsk Oblast, Ukraine",
      "keywords": "",
      "resource": 0,
      "langs": "",
      "langNames": [],
      "runway": null,
      "moreSources": [],
      "videocode": null,
      "target": null,
      "sel_link": null,
      "img_share": ""
    },
    {
      "picpath": "ak-1",
      "picpath_over": "ak-1",
      "id": 22763731,
      "time": "2 днів тому",
      "name": "На Торецьому напрямку вчора відбулися зіткнення в районі Дачного, Діліївки, Торецька та в напрямку Яблунівки, – повідомляє Генеральний штаб Збройних Сил України",
      "source": "https://t.me/lumsrc/12620",
      "lat": "48.41633",
      "lng": 37.61954,
      "picture": "images/22763731_main_picture.jpg",
      "twitpic": "",
      "lang": "uk",
      "video": "",
      "gi": 0,
      "videotype": 0,
      "timestamp": 1749456000,
      "color_id": 1,
      "cat_id": 25,
      "status_id": 0,
      "description": "",
      "udescription": "",
      "picw": 39,
      "pich": 39,
      "picwo": 49,
      "picho": 49,
      "picx": 0,
      "picy": 0,
      "picxo": 0,
      "picyo": 0,
      "ps": [],
      "points": [
        {
          "id": 1,
          "lat": 48.41119,
          "lng": 37.87725
        },
        {
          "id": 2,
          "lat": 48.42002,
          "lng": 37.89082
        },
        {
          "id": 3,
          "lat": 48.4105,
          "lng": 37.8117
        },
        {
          "id": 4,
          "lat": 48.41633,
          "lng": 37.61954
        }
      ],
      "link": "https://liveuamap.com/uk/2025/9-june-09-at-toretsk-axis-clashes-yesterday-near-dachne-dyliyivka",
      "images": [
        {},
        {},
        {}
      ],
      "otherregions": "[]",
      "location": "Donetsk Oblast, Ukraine",
      "keywords": "",
      "resource": 0,
      "langs": "",
      "langNames": [],
      "runway": null,
      "moreSources": [],
      "videocode": null,
      "target": null,
      "sel_link": null,
      "img_share": ""
    },
    {
      "picpath": "ak-1",
      "picpath_over": "ak-1",
      "id": 22763464,
      "time": "3 днів тому",
      "name": "На Торецькому напрямку вчора тривали бої під Торецьком та в напрямку Диліївки та Яблунівки, – повідомляє Генеральний штаб Збройних Сил України",
      "source": "https://t.me/lumsrc/12608",
      "lat": "48.41188",
      "lng": 37.62615,
      "picture": "images/22763464_main_picture.jpg",
      "twitpic": "",
      "lang": "uk",
      "video": "",
      "gi": 0,
      "videotype": 0,
      "timestamp": 1749369600,
      "color_id": 1,
      "cat_id": 25,
      "status_id": 0,
      "description": "",
      "udescription": "",
      "picw": 39,
      "pich": 39,
      "picwo": 49,
      "picho": 49,
      "picx": 0,
      "picy": 0,
      "picxo": 0,
      "picyo": 0,
      "ps": [],
      "points": [],
      "link": "https://liveuamap.com/uk/2025/8-june-08-at-toretsk-axis-clashes-yesterday-near-toretsk",
      "images": [
        {},
        {},
        {}
      ],
      "otherregions": "[]",
      "location": "Donetsk Oblast, Ukraine",
      "keywords": "",
      "resource": 0,
      "langs": "",
      "langNames": [],
      "runway": null,
      "moreSources": [],
      "videocode": null,
      "target": null,
      "sel_link": null,
      "img_share": ""
    },
    {
      "picpath": "ak-1",
      "picpath_over": "ak-1",
      "id": 22763468,
      "time": "3 днів тому",
      "name": "На Краматорському напрямку вчора тривали бої поблизу Часового Яру, Маркового та у напрямку Білої Гори та Предтечиного, повідомляє Генеральний штаб Збройних Сил України",
      "source": "https://t.me/lumsrc/12607",
      "lat": "48.52387",
      "lng": 37.82885,
      "picture": "images/22763468_main_picture.jpg",
      "twitpic": "",
      "lang": "uk",
      "video": "",
      "gi": 0,
      "videotype": 0,
      "timestamp": 1749369600,
      "color_id": 1,
      "cat_id": 25,
      "status_id": 0,
      "description": "",
      "udescription": "",
      "picw": 39,
      "pich": 39,
      "picwo": 49,
      "picho": 49,
      "picx": 0,
      "picy": 0,
      "picxo": 0,
      "picyo": 0,
      "ps": [],
      "points": [
        {
          "id": 5,
          "lat": 48.64242,
          "lng": 37.81151
        },
        {
          "id": 6,
          "lat": 48.58476,
          "lng": 37.83949
        },
        {
          "id": 7,
          "lat": 48.4779,
          "lng": 37.90043
        },
        {
          "id": 8,
          "lat": 48.52387,
          "lng": 37.82885
        }
      ],
      "link": "https://liveuamap.com/uk/2025/8-june-08-at-kramatorsk-axis-clashes-yesterday-near-chasiv",
      "images": [
        {},
        {},
        {}
      ],
      "otherregions": "[]",
      "location": "Donetsk Oblast, Ukraine",
      "keywords": "",
      "resource": 0,
      "langs": "",
      "langNames": [],
      "runway": null,
      "moreSources": [],
      "videocode": null,
      "target": null,
      "sel_link": null,
      "img_share": ""
    },
    {
      "picpath": "ak-1",
      "picpath_over": "ak-1",
      "id": 22763735,
      "time": "2 днів тому",
      "name": "На Краматорському напрямку вчора відбулися зіткнення поблизу Білої Гори, Предтечиного та Курдюмівки, повідомляє Генеральний штаб Збройних Сил України",
      "source": "https://t.me/lumsrc/12619",
      "lat": "48.52607",
      "lng": 37.82682,
      "picture": "images/22763735_main_picture.jpg",
      "twitpic": "",
      "lang": "uk",
      "video": "",
      "gi": 0,
      "videotype": 0,
      "timestamp": 1749456000,
      "color_id": 1,
      "cat_id": 25,
      "status_id": 0,
      "description": "",
      "udescription": "",
      "picw": 39,
      "pich": 39,
      "picwo": 49,
      "picho": 49,
      "picx": 0,
      "picy": 0,
      "picxo": 0,
      "picyo": 0,
      "ps": [],
      "points": [
        {
          "id": 2,
          "lat": 48.49066,
          "lng": 37.90678
        },
        {
          "id": 3,
          "lat": 48.52607,
          "lng": 37.82682
        }
      ],
      "link": "https://liveuamap.com/uk/2025/9-june-08-at-kramatorsk-axis-clashes-yesterday-near-bila",
      "images": [
        {},
        {},
        {}
      ],
      "otherregions": "[]",
      "location": "Donetsk Oblast, Ukraine",
      "keywords": "",
      "resource": 0,
      "langs": "",
      "langNames": [],
      "runway": null,
      "moreSources": [],
      "videocode": null,
      "target": null,
      "sel_link": null,
      "img_share": ""
    },
    {
      "picpath": "ak-1",
      "picpath_over": "ak-1",
      "id": 22763730,
      "time": "2 днів тому",
      "name": "На Сіверському напрямку вчора відбулися зіткнення поблизу Григорівки, Верхньокам'янського та Виймки, – повідомляє Генеральний штаб Збройних Сил України",
      "source": "https://t.me/lumsrc/12618",
      "lat": "48.80854",
      "lng": 38.14024,
      "picture": "images/22763730_main_picture.jpg",
      "twitpic": "",
      "lang": "uk",
      "video": "",
      "gi": 0,
      "videotype": 0,
      "timestamp": 1749456000,
      "color_id": 1,
      "cat_id": 25,
      "status_id": 0,
      "description": "",
      "udescription": "",
      "picw": 39,
      "pich": 39,
      "picwo": 49,
      "picho": 49,
      "picx": 0,
      "picy": 0,
      "picxo": 0,
      "picyo": 0,
      "ps": [],
      "points": [
        {
          "id": 0,
          "lat": 48.85815,
          "lng": 38.18058
        },
        {
          "id": 1,
          "lat": 48.92553,
          "lng": 38.18848
        },
        {
          "id": 2,
          "lat": 48.80854,
          "lng": 38.14024
        }
      ],
      "link": "https://liveuamap.com/uk/2025/9-june-08-at-sieversk-axis-clashes-yesterday-near-hryhorivka",
      "images": [
        {},
        {},
        {}
      ],
      "otherregions": "[]",
      "location": "Donetsk Oblast, Ukraine",
      "keywords": "",
      "resource": 0,
      "langs": "",
      "langNames": [],
      "runway": null,
      "moreSources": [],
      "videocode": null,
      "target": null,
      "sel_link": null,
      "img_share": ""
    },
    {
      "picpath": "ak-1",
      "picpath_over": "ak-1",
      "id": 22763466,
      "time": "3 днів тому",
      "name": "На Сіверському напрямку бойові дії вчора під Верхньокам'янським, - повідомляє Генштаб ЗСУ",
      "source": "https://t.me/lumsrc/12606",
      "lat": "48.85894",
      "lng": 38.18436,
      "picture": "images/22763466_main_picture.jpg",
      "twitpic": "",
      "lang": "uk",
      "video": "",
      "gi": 0,
      "videotype": 0,
      "timestamp": 1749369600,
      "color_id": 1,
      "cat_id": 25,
      "status_id": 0,
      "description": "",
      "udescription": "",
      "picw": 39,
      "pich": 39,
      "picwo": 49,
      "picho": 49,
      "picx": 0,
      "picy": 0,
      "picxo": 0,
      "picyo": 0,
      "ps": [],
      "points": [
        {
          "id": 113,
          "lat": 48.85894,
          "lng": 38.18436
        }
      ],
      "link": "https://liveuamap.com/uk/2025/8-june-08-at-sieversk-axis-clashes-yesterday-near-verkhnokamyanske",
      "images": [
        {},
        {},
        {}
      ],
      "otherregions": "[]",
      "location": "Sieversk",
      "keywords": "",
      "resource": 0,
      "langs": "",
      "langNames": [],
      "runway": null,
      "moreSources": [],
      "videocode": null,
      "target": null,
      "sel_link": null,
      "img_share": ""
    },
    {
      "picpath": "ak-1",
      "picpath_over": "ak-1",
      "id": 22763472,
      "time": "3 днів тому",
      "name": "На Лиманському напрямку вчора відбулися бойові дії поблизу Греківки, Нового Миру, Рідкодуба, Зеленої Долини, Торського та Білогорівки, - повідомляє Генштаб ЗСУ",
      "source": "https://t.me/lumsrc/12605",
      "lat": "48.92113",
      "lng": 38.25096,
      "picture": "images/22763472_main_picture.jpg",
      "twitpic": "",
      "lang": "uk",
      "video": "",
      "gi": 0,
      "videotype": 0,
      "timestamp": 1749371760,
      "color_id": 1,
      "cat_id": 25,
      "status_id": 0,
      "description": "",
      "udescription": "",
      "picw": 39,
      "pich": 39,
      "picwo": 49,
      "picho": 49,
      "picx": 0,
      "picy": 0,
      "picxo": 0,
      "picyo": 0,
      "ps": [],
      "points": [
        {
          "id": 9,
          "lat": 49.17899,
          "lng": 37.77683
        },
        {
          "id": 10,
          "lat": 49.25547,
          "lng": 37.89408
        },
        {
          "id": 11,
          "lat": 49.2141,
          "lng": 37.84567
        },
        {
          "id": 12,
          "lat": 49.12809,
          "lng": 37.82531
        },
        {
          "id": 13,
          "lat": 49.01703,
          "lng": 37.9636
        },
        {
          "id": 14,
          "lat": 48.92113,
          "lng": 38.25096
        }
      ],
      "link": "https://liveuamap.com/uk/2025/8-june-08-at-lyman-axis-clashes-yesterday-near-hrekivka-novyy",
      "images": [
        {},
        {},
        {}
      ],
      "otherregions": "[]",
      "location": "Luhansk Oblast, Ukraine",
      "keywords": "",
      "resource": 0,
      "langs": "",
      "langNames": [],
      "runway": null,
      "moreSources": [],
      "videocode": null,
      "target": null,
      "sel_link": null,
      "img_share": ""
    },
    {
      "picpath": "ak-1",
      "picpath_over": "ak-1",
      "id": 22763738,
      "time": "2 днів тому",
      "name": "На Лиманському напрямку вчора відбулися бойові дії поблизу Греківки, Нового Миру, Рідкодубів, Зеленої Долини та в напрямку Чернещини, Торського, Серебрянського лісу, - повідомляє Генштаб ЗСУ.",
      "source": "https://t.me/lumsrc/12617",
      "lat": "48.95849",
      "lng": 38.10127,
      "picture": "images/22763738_main_picture.jpg",
      "twitpic": "",
      "lang": "uk",
      "video": "",
      "gi": 0,
      "videotype": 0,
      "timestamp": 1749456000,
      "color_id": 1,
      "cat_id": 25,
      "status_id": 0,
      "description": "",
      "udescription": "",
      "picw": 39,
      "pich": 39,
      "picwo": 49,
      "picho": 49,
      "picx": 0,
      "picy": 0,
      "picxo": 0,
      "picyo": 0,
      "ps": [],
      "points": [
        {
          "id": 5,
          "lat": 49.25592,
          "lng": 37.89133
        },
        {
          "id": 6,
          "lat": 49.21679,
          "lng": 37.84
        },
        {
          "id": 7,
          "lat": 49.17539,
          "lng": 37.78423
        },
        {
          "id": 8,
          "lat": 49.13161,
          "lng": 37.82232
        },
        {
          "id": 9,
          "lat": 49.30529,
          "lng": 37.89957
        },
        {
          "id": 10,
          "lat": 49.04725,
          "lng": 37.95708
        },
        {
          "id": 11,
          "lat": 48.95849,
          "lng": 38.10127
        }
      ],
      "link": "https://liveuamap.com/uk/2025/9-june-08-at-lyman-axis-clashes-yesterday-near-hrekivka-novyy",
      "images": [
        {},
        {},
        {}
      ],
      "otherregions": "[]",
      "location": "Luhansk Oblast, Ukraine",
      "keywords": "",
      "resource": 0,
      "langs": "",
      "langNames": [],
      "runway": null,
      "moreSources": [],
      "videocode": null,
      "target": null,
      "sel_link": null,
      "img_share": ""
    },
    {
      "picpath": "ak-1",
      "picpath_over": "ak-1",
      "id": 22763742,
      "time": "2 днів тому",
      "name": "На Куп'янському напрямку вчора відбулися бойові дії поблизу Степової Новоселівки, Глушківки та Загризового, - повідомляє Генштаб ЗСУ",
      "source": "https://t.me/lumsrc/12616",
      "lat": "49.49744",
      "lng": 37.71212,
      "picture": "images/22763742_main_picture.jpg",
      "twitpic": "",
      "lang": "uk",
      "video": "",
      "gi": 0,
      "videotype": 0,
      "timestamp": 1749456000,
      "color_id": 1,
      "cat_id": 25,
      "status_id": 0,
      "description": "",
      "udescription": "",
      "picw": 39,
      "pich": 39,
      "picwo": 49,
      "picho": 49,
      "picx": 0,
      "picy": 0,
      "picxo": 0,
      "picyo": 0,
      "ps": [],
      "points": [
        {
          "id": 59,
          "lat": 49.66595,
          "lng": 37.83039
        },
        {
          "id": 60,
          "lat": 49.58822,
          "lng": 37.72293
        },
        {
          "id": 61,
          "lat": 49.49744,
          "lng": 37.71212
        }
      ],
      "link": "https://liveuamap.com/uk/2025/9-june-08-at-kupyansk-axis-clashes-yesterday-near-stepova",
      "images": [
        {},
        {},
        {}
      ],
      "otherregions": "[]",
      "location": "Kharkiv Oblast, Ukraine",
      "keywords": "",
      "resource": 0,
      "langs": "",
      "langNames": [],
      "runway": null,
      "moreSources": [],
      "videocode": null,
      "target": null,
      "sel_link": null,
      "img_share": ""
    },
    {
      "picpath": "ak-1",
      "picpath_over": "ak-1",
      "id": 22763469,
      "time": "3 днів тому",
      "name": "Вчора на Куп'янському напрямку тривали бої біля Степової Новоселівки, повідомляє Генеральний штаб Збройних Сил України",
      "source": "https://t.me/lumsrc/12604",
      "lat": "49.66695",
      "lng": 37.81116,
      "picture": "images/22763469_main_picture.jpg",
      "twitpic": "",
      "lang": "uk",
      "video": "",
      "gi": 0,
      "videotype": 0,
      "timestamp": 1749369600,
      "color_id": 1,
      "cat_id": 25,
      "status_id": 0,
      "description": "",
      "udescription": "",
      "picw": 39,
      "pich": 39,
      "picwo": 49,
      "picho": 49,
      "picx": 0,
      "picy": 0,
      "picxo": 0,
      "picyo": 0,
      "ps": [],
      "points": [],
      "link": "https://liveuamap.com/uk/2025/8-june-08-at-kupyansk-axis-clashes-yesterday-near-stepova",
      "images": [
        {},
        {},
        {}
      ],
      "otherregions": "[]",
      "location": "Kupiansk",
      "keywords": "",
      "resource": 0,
      "langs": "",
      "langNames": [],
      "runway": null,
      "moreSources": [],
      "videocode": null,
      "target": null,
      "sel_link": null,
      "img_share": ""
    },
    {
      "picpath": "ak-1",
      "picpath_over": "ak-1",
      "id": 22763473,
      "time": "3 днів тому",
      "name": "На Харківському напрямку вчора відбулися бойові дії під Вовчанськом, Вовчанськими Хуторами та Західним, - повідомляє Генштаб ЗСУ",
      "source": "https://t.me/lumsrc/12603",
      "lat": "49.8259",
      "lng": 37.59762,
      "picture": "images/22763473_main_picture.jpg",
      "twitpic": "",
      "lang": "uk",
      "video": "",
      "gi": 0,
      "videotype": 0,
      "timestamp": 1749371760,
      "color_id": 1,
      "cat_id": 25,
      "status_id": 0,
      "description": "",
      "udescription": "",
      "picw": 39,
      "pich": 39,
      "picwo": 49,
      "picho": 49,
      "picx": 0,
      "picy": 0,
      "picxo": 0,
      "picyo": 0,
      "ps": [],
      "points": [
        {
          "id": 15,
          "lat": 50.31422,
          "lng": 37.0253
        },
        {
          "id": 16,
          "lat": 49.8259,
          "lng": 37.59762
        }
      ],
      "link": "https://liveuamap.com/uk/2025/8-june-08-at-kharkiv-axis-clashes-yesterday-near-vovchansk",
      "images": [
        {},
        {},
        {}
      ],
      "otherregions": "[]",
      "location": "Kharkiv Oblast, Ukraine",
      "keywords": "",
      "resource": 0,
      "langs": "",
      "langNames": [],
      "runway": null,
      "moreSources": [],
      "videocode": null,
      "target": null,
      "sel_link": null,
      "img_share": ""
    },
    {
      "picpath": "ak-1",
      "picpath_over": "ak-1",
      "id": 22763729,
      "time": "2 днів тому",
      "name": "У Курській області українські війська відбили 27 штурмів російської армії, - повідомляє Генштаб ЗСУ",
      "source": "https://t.me/lumsrc/12626",
      "lat": "51.13497",
      "lng": 35.16116,
      "picture": "images/22763729_main_picture.jpg",
      "twitpic": "",
      "lang": "uk",
      "video": "",
      "gi": 0,
      "videotype": 0,
      "timestamp": 1749456000,
      "color_id": 1,
      "cat_id": 25,
      "status_id": 0,
      "description": "",
      "udescription": "",
      "picw": 39,
      "pich": 39,
      "picwo": 49,
      "picho": 49,
      "picx": 0,
      "picy": 0,
      "picxo": 0,
      "picyo": 0,
      "ps": [],
      "points": [
        {
          "id": 36,
          "lat": 51.19958,
          "lng": 34.85079
        },
        {
          "id": 37,
          "lat": 51.13497,
          "lng": 35.16116
        }
      ],
      "link": "https://liveuamap.com/uk/2025/9-june-08-in-kursk-region-ukrainian-forces-have-repelled",
      "images": [
        {},
        {},
        {}
      ],
      "otherregions": "[]",
      "location": "Kursk",
      "keywords": "",
      "resource": 0,
      "langs": "",
      "langNames": [],
      "runway": null,
      "moreSources": [],
      "videocode": null,
      "target": null,
      "sel_link": null,
      "img_share": ""
    },
    {
      "picpath": "ak-1",
      "picpath_over": "ak-1",
      "id": 22763463,
      "time": "3 днів тому",
      "name": "У Курській області українські війська відбили 31 штурм російської армії, - повідомляє Генштаб ЗСУ",
      "source": "https://t.me/lumsrc/12614",
      "lat": "51.21715",
      "lng": 35.05119,
      "picture": "images/22763463_main_picture.jpg",
      "twitpic": "",
      "lang": "uk",
      "video": "",
      "gi": 0,
      "videotype": 0,
      "timestamp": 1749369600,
      "color_id": 1,
      "cat_id": 25,
      "status_id": 0,
      "description": "",
      "udescription": "",
      "picw": 39,
      "pich": 39,
      "picwo": 49,
      "picho": 49,
      "picx": 0,
      "picy": 0,
      "picxo": 0,
      "picyo": 0,
      "ps": [],
      "points": [
        {
          "id": 0,
          "lat": 51.1853,
          "lng": 34.81773
        },
        {
          "id": 1,
          "lat": 51.11292,
          "lng": 35.18303
        },
        {
          "id": 2,
          "lat": 51.21715,
          "lng": 35.05119
        }
      ],
      "link": "https://liveuamap.com/uk/2025/8-june-08-in-kursk-region-ukrainian-forces-have-repelled",
      "images": [
        {},
        {},
        {}
      ],
      "otherregions": "[]",
      "location": "Kursk Oblast, Russia",
      "keywords": "",
      "resource": 0,
      "langs": "",
      "langNames": [],
      "runway": null,
      "moreSources": [],
      "videocode": null,
      "target": null,
      "sel_link": null,
      "img_share": ""
    }
  ]
}